diracx/routers/__init__.py
diracx/routers/access_policies.py
diracx/routers/configuration.py
diracx/routers/dependencies.py
diracx/routers/factory.py
diracx/routers/fastapi_classes.py
diracx/routers/otel.py
diracx/routers/py.typed
diracx/routers/auth/__init__.py
diracx/routers/auth/authorize_code_flow.py
diracx/routers/auth/device_flow.py
diracx/routers/auth/management.py
diracx/routers/auth/token.py
diracx/routers/auth/utils.py
diracx/routers/auth/well_known.py
diracx/routers/health/__init__.py
diracx/routers/health/probes.py
diracx/routers/jobs/__init__.py
diracx/routers/jobs/access_policies.py
diracx/routers/jobs/legacy.py
diracx/routers/jobs/query.py
diracx/routers/jobs/sandboxes.py
diracx/routers/jobs/status.py
diracx/routers/jobs/submission.py
diracx/routers/utils/__init__.py
diracx/routers/utils/users.py
diracx_routers-0.0.7.dist-info/METADATA
diracx_routers-0.0.7.dist-info/WHEEL
diracx_routers-0.0.7.dist-info/entry_points.txt
diracx_routers-0.0.7.dist-info/RECORD
