Metadata-Version: 2.4
Name: diracx-routers
Version: 0.0.7
Summary: TODO
License: GPL-3.0-only
Classifier: Intended Audience :: Science/Research
Classifier: License :: OSI Approved :: GNU General Public License v3 (GPLv3)
Classifier: Programming Language :: Python :: 3
Classifier: Topic :: Scientific/Engineering
Classifier: Topic :: System :: Distributed Computing
Requires-Python: >=3.11
Requires-Dist: cachetools
Requires-Dist: diracx-core
Requires-Dist: diracx-db
Requires-Dist: diracx-logic
Requires-Dist: fastapi>=0.121.0
Requires-Dist: httpx
Requires-Dist: joserfc
Requires-Dist: opentelemetry-api
Requires-Dist: opentelemetry-exporter-otlp
Requires-Dist: opentelemetry-instrumentation-fastapi
Requires-Dist: opentelemetry-instrumentation-logging
Requires-Dist: opentelemetry-sdk
Requires-Dist: pydantic>=2.10
Requires-Dist: python-dotenv
Requires-Dist: python-multipart
Requires-Dist: uvicorn
Provides-Extra: testing
Requires-Dist: diracx-testing; extra == 'testing'
Requires-Dist: freezegun; extra == 'testing'
Requires-Dist: moto[server]; extra == 'testing'
Requires-Dist: pyjwt; extra == 'testing'
Requires-Dist: pytest-httpx; extra == 'testing'
Provides-Extra: types
Requires-Dist: types-cachetools; extra == 'types'
Requires-Dist: types-python-dateutil; extra == 'types'
Requires-Dist: types-pyyaml; extra == 'types'
